imports/__init__.py
imports/analyze.py
smart_pip/__init__.py
smart_pip_magic-0.1.2.dist-info/LICENSE
smart_pip_magic-0.1.2.dist-info/METADATA
smart_pip_magic-0.1.2.dist-info/WHEEL
smart_pip_magic-0.1.2.dist-info/top_level.txt
smart_pip_magic-0.1.2.dist-info/RECORD
