Metadata-Version: 2.1
Name: smart-pip-magic
Version: 0.1.2
Summary: A alternative pip magic to jupyter's %pip. It shows if you need to restart python after %smart_pip install
Author-email: Xiao Chen <xiao.chen@databricks.com>
Project-URL: Homepage, https://github.com/xiaochen-db/smart-pip-magic
Project-URL: Issues, https://github.com/xiaochen-db/smart-pip-magic/issues
Classifier: Programming Language :: Python :: 3
Classifier: Operating System :: OS Independent
Requires-Python: >=3.9
License-File: LICENSE
Requires-Dist: ipython >=6.0.0
Provides-Extra: dev
Requires-Dist: ruff ; extra == 'dev'
Requires-Dist: build ; extra == 'dev'
Requires-Dist: twine ; extra == 'dev'
Requires-Dist: pytest ; extra == 'dev'
